{
  "posts": [
    {
      "id": "1",
      "title": "a titlegtgrtgtgrtgrgrt",
      "views": 100
    },
    {
      "id": "2",
      "title": "gerg title",
      "views": 2500
    },
    {
      "id": "3",
      "title": "gerger title",
      "views": 20110
    },
    {
      "id": "4",
      "title": "gergerger title",
      "views": 2010
    },
    {
      "id": "5",
      "title": "gregergergerger title",
      "views": 2080
    },
    {
      "id": "6",
      "title": "test title",
      "views": 5200
    },
    {
      "id": "7",
      "title": "kaya title",
      "views": 200
    },
    {
      "id": "8",
      "title": "bimd title",
      "views": 2030
    },
    {
      "id": "9",
      "title": "ptaga title",
      "views": 2020
    }
  ],
  "name": "sanjeev"
}